LICENSE
pgmask/__init__.py
pgmask/basiclayer.py
pgmask/dataframelayer.py
pgmask-0.1.2.dist-info/LICENSE
pgmask-0.1.2.dist-info/WHEEL
pgmask-0.1.2.dist-info/METADATA
pgmask-0.1.2.dist-info/RECORD
